README.md
setup.py
hypium/__init__.py
hypium/__main__.py
hypium/exception.py
hypium/version.py
hypium.egg-info/PKG-INFO
hypium.egg-info/SOURCES.txt
hypium.egg-info/dependency_links.txt
hypium.egg-info/requires.txt
hypium.egg-info/top_level.txt
hypium/action/__init__.py
hypium/action/app/__init__.py
hypium/action/app/launcher.py
hypium/action/device/__init__.py
hypium/action/device/plugin_mix_in.py
hypium/action/device/uidriver.py
hypium/action/host/__init__.py
hypium/action/host/cv.py
hypium/action/host/host.py
hypium/advance/__init__.py
hypium/advance/pop_up_window_handler.py
hypium/advance/pop_window_rules.py
hypium/advance/deveco_testing/__init__.py
hypium/advance/deveco_testing/dvt_logger.py
hypium/advance/deveco_testing/dvt_step_info.py
hypium/advance/deveco_testing/metric.py
hypium/advance/deveco_testing/step.py
hypium/advance/deveco_testing/task_event_manager.py
hypium/advance/deveco_testing/utils.py
hypium/checker/__init__.py
hypium/checker/assertion.py
hypium/dfx/__init__.py
hypium/dfx/data
hypium/dfx/init_status_manager.py
hypium/dfx/privacy_policy.md
hypium/dfx/tracker.py
hypium/docs/__init__.py
hypium/docs/__main__.py
hypium/docs/hypium_api_6.0.7.210.md
hypium/model/__init__.py
hypium/model/basic_data_type.py
hypium/model/constant.py
hypium/model/driver_config.py
hypium/uidriver/__init__.py
hypium/uidriver/arkuidriver.py
hypium/uidriver/by.py
hypium/uidriver/component_exception_handler.py
hypium/uidriver/device_connector.py
hypium/uidriver/frontend_api.py
hypium/uidriver/gesture.py
hypium/uidriver/logger.py
hypium/uidriver/pointer_matrix.py
hypium/uidriver/proxy_v1.py
hypium/uidriver/proxy_v2.py
hypium/uidriver/remote_object_manager.py
hypium/uidriver/setup_device.py
hypium/uidriver/shell.py
hypium/uidriver/system_info.py
hypium/uidriver/uicomponent.py
hypium/uidriver/uiwindow.py
hypium/uidriver/common/__init__.py
hypium/uidriver/common/config_helper.py
hypium/uidriver/common/device_type_helper.py
hypium/uidriver/common/enhanced_component_finder.py
hypium/uidriver/common/report_helper.py
hypium/uidriver/common/uicomponent_helper.py
hypium/uidriver/interface/__init__.py
