Metadata-Version: 2.1
Name: hypium
Version: 6.0.7.210
Summary: A UI test framework for HarmonyOS devices
Provides-Extra: advance
Provides-Extra: qr
